textuv/__init__.py
textuv/cli.py
textuv-0.1.4.dist-info/METADATA
textuv-0.1.4.dist-info/WHEEL
textuv-0.1.4.dist-info/entry_points.txt
textuv-0.1.4.dist-info/RECORD
