Metadata-Version: 2.4
Name: textuv
Version: 0.1.4
Summary: CLI to scaffold a Textual + uv application
Project-URL: Homepage, https://github.com/totsuxyz/textuv
Project-URL: Repository, https://github.com/totsuxyz/textuv
Project-URL: Issues, https://github.com/totsuxyz/textuv/issues
Author-email: yosui <yosui262@gmail.com>
License: MIT
Classifier: License :: OSI Approved :: MIT License
Classifier: Operating System :: OS Independent
Classifier: Programming Language :: Python :: 3
Requires-Python: >=3.12
Requires-Dist: typer>=0.9.0
Provides-Extra: dev
Requires-Dist: black>=23.0.0; extra == 'dev'
Requires-Dist: pytest>=7.0.0; extra == 'dev'
Requires-Dist: ruff>=0.1.0; extra == 'dev'
